dolphot_lc/__init__.py
dolphot_lc/dlc_params.py
dolphot_lc/dolphot_scrips.py
dolphot_lc/image_sub.py
dolphot_lc/process_ims.py
dolphot_lc-0.0.2.dist-info/LICENCE
dolphot_lc-0.0.2.dist-info/METADATA
dolphot_lc-0.0.2.dist-info/WHEEL
dolphot_lc-0.0.2.dist-info/top_level.txt
dolphot_lc-0.0.2.dist-info/RECORD
